pyrkbun/__init__.py
pyrkbun/cli.py
pyrkbun/const.py
pyrkbun/dns.py
pyrkbun/pricing.py
pyrkbun/ssl.py
pyrkbun/util.py
pyrkbun-1.2.1.dist-info/LICENSE
pyrkbun-1.2.1.dist-info/METADATA
pyrkbun-1.2.1.dist-info/WHEEL
pyrkbun-1.2.1.dist-info/entry_points.txt
pyrkbun-1.2.1.dist-info/top_level.txt
pyrkbun-1.2.1.dist-info/RECORD
