Metadata-Version: 2.1
Name: pyrkbun
Version: 1.2.1
Summary: An unoffical Python library and CLI for the Porkbun domain registrars API
Author: jxg81
License: Apache License
Project-URL: Homepage, https://github.com/jxg81/pyrkbun
Keywords: API,Porkbun,DNS,Registrar
Classifier: License :: OSI Approved :: Apache Software License
Classifier: Programming Language :: Python
Classifier: Programming Language :: Python :: 3.9
Classifier: Programming Language :: Python :: 3.10
Classifier: Natural Language :: English
Requires-Python: >=3.9
License-File: LICENSE
Requires-Dist: httpx[http2]
Requires-Dist: colorama
Provides-Extra: dev
Requires-Dist: python-dotenv ; extra == 'dev'
Requires-Dist: setuptools ; extra == 'dev'
